btnamespace/__init__.py
btnamespace/_version.py
btnamespace/actions.py
btnamespace/compat.py
btnamespace/namespace.py
btnamespace/patch.py
btnamespace/schemas.py
btnamespace/shared.py
btnamespace-2.1.1.dist-info/LICENSE
btnamespace-2.1.1.dist-info/METADATA
btnamespace-2.1.1.dist-info/WHEEL
btnamespace-2.1.1.dist-info/top_level.txt
btnamespace-2.1.1.dist-info/RECORD
