Metadata-Version: 2.1
Name: btnamespace
Version: 2.1.1
Summary: Isolate state on the Braintree sandbox during testing.
Home-page: https://github.com/venmo/btnamespace
Author: Simon Weber
Author-email: simon@venmo.com
License: MIT
Platform: UNKNOWN
Classifier: Development Status :: 5 - Production/Stable
Classifier: Intended Audience :: Developers
Classifier: License :: OSI Approved :: MIT License
Classifier: Programming Language :: Python
Classifier: Programming Language :: Python :: 2
Classifier: Programming Language :: Python :: 2.7
Classifier: Programming Language :: Python :: 3
Classifier: Programming Language :: Python :: 3.5
Classifier: Programming Language :: Python :: 3.7
Requires-Python: >=2.7, !=3.0.*, !=3.1.*, !=3.2.*, !=3.3.*, !=3.4.*, !=3.6.*
License-File: LICENSE
Requires-Dist: future (>=0.18.2)
Requires-Dist: mock
Requires-Dist: bidict (<0.19,>=0.18.4) ; python_version <= "2.7"
Requires-Dist: braintree (<4,>=3.46.0) ; python_version <= "2.7"
Requires-Dist: bidict (>=0.18.4) ; python_version > "2.7"
Requires-Dist: braintree (>=3.46.0) ; python_version > "2.7"
